2to3-1.0.dist-info/METADATA
2to3-1.0.dist-info/RECORD
2to3-1.0.dist-info/WHEEL
2to3-1.0.dist-info/entry_points.txt
2to3-1.0.dist-info/top_level.txt
cmd_2to3/__init__.py
cmd_2to3/__main__.py
