Metadata-Version: 1.0
Name: 2to3
Version: 1.0
Summary: Adds the 2to3 command directly to entry_points.
Home-page: UNKNOWN
Author: xoviat
Author-email: xoviat@gmail.com
License: MIT
Keywords: 2to3
Platform: UNKNOWN
